Metadata-Version: 2.1
Name: floorutil
Version: 1.0.3
Summary: sampleutil
Home-page: https://github.com/xuzhili/FloorUtil
Author: xuzhili
Author-email: xuzhili@znds.com
License: MIT
Keywords: send email
Platform: UNKNOWN
Classifier: License :: OSI Approved :: MIT License
Classifier: Programming Language :: Python
Classifier: Intended Audience :: Developers
Classifier: Operating System :: OS Independent
